msh/msh_t.py
msh/loadmsh.py
msh/__init__.py
inpoly/inpoly2.py
inpoly/inpoly_.cpython-37m-x86_64-linux-gnu.so
inpoly/__init__.py
inpoly-0.2.0.dist-info/LICENSE.md
inpoly-0.2.0.dist-info/top_level.txt
inpoly-0.2.0.dist-info/RECORD
inpoly-0.2.0.dist-info/METADATA
inpoly-0.2.0.dist-info/WHEEL
