Metadata-Version: 2.1
Name: inpoly
Version: 0.2.0
Summary: Fast point(s)-in-polygon queries.
Home-page: https://github.com/dengwirda/inpoly-python
Author: Darren Engwirda and Keith Roberts
Author-email: d.engwirda@gmail.com
License: custom
Keywords: Point-in-Polygon Geometry GIS
Platform: UNKNOWN
Classifier: Development Status :: 4 - Beta
Classifier: Operating System :: OS Independent
Classifier: Intended Audience :: Science/Research
Classifier: Programming Language :: Python
Classifier: Programming Language :: Python :: 3
Classifier: Topic :: Scientific/Engineering
Classifier: Topic :: Scientific/Engineering :: Mathematics
Classifier: Topic :: Scientific/Engineering :: Physics
Classifier: Topic :: Scientific/Engineering :: Visualization
Classifier: Topic :: Scientific/Engineering :: GIS
Requires-Python: >=3.3.0
Requires-Dist: numpy
